dinuc_shuf-0.1.0b1.dist-info/METADATA
dinuc_shuf-0.1.0b1.dist-info/WHEEL
dinuc_shuf-0.1.0b1.dist-info/licenses/LICENSE
dinuc_shuf/__init__.py
dinuc_shuf/main.py
dinuc_shuf/dinuc_shuf.abi3.so
dinuc_shuf-0.1.0b1.dist-info/RECORD
