Metadata-Version: 2.4
Name: dinuc_shuf
Version: 0.1.0b1
Classifier: Programming Language :: Rust
Classifier: Programming Language :: Python :: Implementation :: CPython
Classifier: Programming Language :: Python :: Implementation :: PyPy
Classifier: Development Status :: 4 - Beta
Requires-Dist: numpy >=1.16.0
License-File: LICENSE
Summary: A utility for shuffling biological sequences while preserving dinucleotide frequencies.
Author: Austin Wang
License: MIT
Requires-Python: >=3.8
Project-URL: Homepage, https://github.com/austintwang/dinuc_shuf
Project-URL: Documentation, https://austintwang.github.io/dinuc_shuf
Project-URL: Repository, https://github.com/austintwang/dinuc_shuf.git
Project-URL: Bug Tracker, https://github.com/austintwang/dinuc_shuf/issues
